setup.py
verysimplemodule_anna/__init__.py
verysimplemodule_anna/add.py
verysimplemodule_anna/subtract.py
verysimplemodule_anna.egg-info/PKG-INFO
verysimplemodule_anna.egg-info/SOURCES.txt
verysimplemodule_anna.egg-info/dependency_links.txt
verysimplemodule_anna.egg-info/requires.txt
verysimplemodule_anna.egg-info/top_level.txt
verysimplemodule_anna/extra/__init__.py
verysimplemodule_anna/extra/divide.py
verysimplemodule_anna/extra/multiply.py